coquery/__init__.py
coquery/__main__.py
coquery/bibliography.py
coquery/coquery.py
coquery/corpus.py
coquery/corpusbuilder.py
coquery/defines.py
coquery/documents.py
coquery/errors.py
coquery/functions.py
coquery/options.py
coquery/queries.py
coquery/session.py
coquery/sqlhelper.py
coquery/sqlwrap.py
coquery/textgrids.py
coquery/tokens.py
coquery/transpose.py
coquery/unicode.py
coquery/gui/__init__.py
coquery/gui/about.py
coquery/gui/app.py
coquery/gui/classes.py
coquery/gui/connectionconfiguration.py
coquery/gui/contextviewer.py
coquery/gui/corpusbuilder_interface.py
coquery/gui/corpusmanager.py
coquery/gui/createuser.py
coquery/gui/csvoptions.py
coquery/gui/errorbox.py
coquery/gui/figureoptions.py
coquery/gui/filterviewer.py
coquery/gui/functionapply.py
coquery/gui/helpviewer.py
coquery/gui/linkselect.py
coquery/gui/logfile.py
coquery/gui/mysql_guide.py
coquery/gui/nltkdatafiles.py
coquery/gui/pyqt_compat.py
coquery/gui/removecorpus.py
coquery/gui/renamecolumn.py
coquery/gui/settings.py
coquery/gui/stopwords.py
coquery/gui/uniqueviewer.py
coquery/gui/visualization.py
coquery/gui/ui/__init__.py
coquery/gui/ui/aboutUi.py
coquery/gui/ui/connectionConfigurationUi.py
coquery/gui/ui/contextViewerUi.py
coquery/gui/ui/coqueryUi.py
coquery/gui/ui/corpusInstallerUi.py
coquery/gui/ui/corpusManagerUi.py
coquery/gui/ui/createUserUi.py
coquery/gui/ui/csvOptionsUi.py
coquery/gui/ui/errorUi.py
coquery/gui/ui/figureOptionsUi.py
coquery/gui/ui/functionApplyUi.py
coquery/gui/ui/helpViewerUi.py
coquery/gui/ui/linkselectUi.py
coquery/gui/ui/logfileUi.py
coquery/gui/ui/mysql_guideUi.py
coquery/gui/ui/nltkDatafilesUi.py
coquery/gui/ui/queryfilterUi.py
coquery/gui/ui/removeCorpusUi.py
coquery/gui/ui/renameColumnUi.py
coquery/gui/ui/settingsUi.py
coquery/gui/ui/stopwordsUi.py
coquery/gui/ui/uniqueViewerUi.py
coquery/gui/ui/visualizerUi.py
coquery/help/.buildinfo
coquery/help/conf.py
coquery/help/index.html
coquery-0.9.2.dist-info/DESCRIPTION.rst
coquery-0.9.2.dist-info/METADATA
coquery-0.9.2.dist-info/RECORD
coquery-0.9.2.dist-info/WHEEL
coquery-0.9.2.dist-info/entry_points.txt
coquery-0.9.2.dist-info/metadata.json
coquery-0.9.2.dist-info/top_level.txt
