Metadata-Version: 2.0
Name: coquery
Version: 0.9.2
Summary: Coquery: A free corpus query tool
Home-page: http://www.coquery.org
Author: Gero Kunter
Author-email: gero.kunter@coquery.org
License: GPL3
Keywords: corpus linguistics query corpora analysis visualization
Platform: UNKNOWN
Classifier: Development Status :: 4 - Beta
Classifier: Intended Audience :: Science/Research
Classifier: License :: OSI Approved :: GNU General Public License v3 (GPLv3)
Classifier: Operating System :: MacOS
Classifier: Operating System :: Microsoft :: Windows
Classifier: Operating System :: POSIX
Classifier: Programming Language :: Python :: 2
Classifier: Programming Language :: Python :: 2.7
Classifier: Programming Language :: Python :: 3
Classifier: Programming Language :: Python :: 3.3
Classifier: Programming Language :: Python :: 3.4
Classifier: Topic :: Education
Classifier: Topic :: Scientific/Engineering
Classifier: Topic :: Scientific/Engineering :: Information Analysis
Classifier: Topic :: Scientific/Engineering :: Visualization
Classifier: Topic :: Text Processing :: Linguistic
Requires-Dist: pandas
Requires-Dist: sqlalchemy
